stl_to_h5m/__init__.py
stl_to_h5m/_version.py
stl_to_h5m/core.py
stl_to_h5m-0.2.3.dist-info/LICENSE.txt
stl_to_h5m-0.2.3.dist-info/METADATA
stl_to_h5m-0.2.3.dist-info/WHEEL
stl_to_h5m-0.2.3.dist-info/top_level.txt
stl_to_h5m-0.2.3.dist-info/RECORD
