Metadata-Version: 2.1
Name: stl-to-h5m
Version: 0.2.3
Summary: Converts STL files to a DAGMC h5m file using PyMoab
Author-email: Jonathan Shimwell <mail@jshimwell.com>
License: MIT License        
Project-URL: Homepage, https://github.com/fusion-energy/stl_to_h5m
Project-URL: Bug Tracker, https://github.com/fusion-energy/stl_to_h5m/issues
Keywords: stl,cad,dagmc,neutronics,openmc,h5m
Classifier: Programming Language :: Python :: 3
Classifier: License :: OSI Approved :: MIT License
Classifier: Operating System :: OS Independent
Requires-Python: >=3.8
License-File: LICENSE.txt
Requires-Dist: numpy (>=1.21.1)
Provides-Extra: tests
Requires-Dist: pytest ; extra == 'tests'
Requires-Dist: dagmc-h5m-file-inspector ; extra == 'tests'
